eopod/__init__.py
eopod/_eopod_cli.py
eopod/_utils.py
eopod-0.0.33.dist-info/WHEEL
eopod-0.0.33.dist-info/entry_points.txt
eopod-0.0.33.dist-info/METADATA
eopod-0.0.33.dist-info/RECORD
