Metadata-Version: 2.3
Name: eopod
Version: 0.0.33
Summary: eopod is a streamlined command execution tool designed to run and manage operations on Google Cloud Pods efficiently
Keywords: eopod
Author: Erfan Zare Chavoshi
Author-email: Erfan Zare Chavoshi <Erfanzare810@gmail.com>
License: Apache-2.0
Classifier: Development Status :: 3 - Alpha
Classifier: Intended Audience :: Developers
Classifier: Topic :: Scientific/Engineering :: Artificial Intelligence
Classifier: License :: OSI Approved :: Apache Software License
Classifier: Programming Language :: Python :: 3.11
Classifier: Programming Language :: Python :: 3.12
Classifier: Programming Language :: Python :: 3.13
Requires-Dist: click>=8.0
Requires-Dist: rich>=13.7.0
Requires-Dist: pyyaml>=6.0.1
Requires-Dist: tpu-info==0.4.0
Requires-Python: >=3.11, <3.14
Project-URL: Documentation, https://eopod.readthedocs.io/en/latest/
Project-URL: Homepage, https://github.com/erfanzar/eopod
Project-URL: Repository, https://github.com/erfanzar/eopod
